azureml/__init__.py
azureml/registry/__init__.py
azureml/registry/_cli/__init__.py
azureml/registry/_cli/registry_syndication_cli.py
azureml/registry/_cli/repo2registry_cli.py
azureml/registry/_rest_client/__init__.py
azureml/registry/_rest_client/arm_client.py
azureml/registry/_rest_client/base_rest_client.py
azureml/registry/_rest_client/registry_management_client.py
azureml/registry/_rest_client/registry_model_client.py
azureml/registry/data/__init__.py
azureml/registry/data/asset.yaml.template
azureml/registry/data/description.md.template
azureml/registry/data/evaluation.md.template
azureml/registry/data/model-variant.schema.json
azureml/registry/data/model.schema.json
azureml/registry/data/model.yaml.template
azureml/registry/data/notes.md.template
azureml/registry/data/validate_model_schema.py
azureml/registry/data/validate_model_variant_schema.py
azureml/registry/mgmt/__init__.py
azureml/registry/mgmt/asset_management.py
azureml/registry/mgmt/create_asset_template.py
azureml/registry/mgmt/create_manifest.py
azureml/registry/mgmt/create_model_spec.py
azureml/registry/mgmt/model_management.py
azureml/registry/mgmt/syndication_manifest.py
azureml/registry/mgmt/util.py
azureml/registry/tools/__init__.py
azureml/registry/tools/config.py
azureml/registry/tools/create_or_update_assets.py
azureml/registry/tools/registry_utils.py
azureml/registry/tools/repo2registry_config.py
azureml_registry_tools-0.1.0a34.dist-info/licenses/LICENSE.txt
azureml_registry_tools-0.1.0a34.dist-info/METADATA
azureml_registry_tools-0.1.0a34.dist-info/WHEEL
azureml_registry_tools-0.1.0a34.dist-info/entry_points.txt
azureml_registry_tools-0.1.0a34.dist-info/top_level.txt
azureml_registry_tools-0.1.0a34.dist-info/RECORD
