Metadata-Version: 2.4
Name: azureml-registry-tools
Version: 0.1.0a34
Summary: AzureML Registry tools and CLI
Author: Microsoft Corp
License: https://aka.ms/azureml-sdk-license
Requires-Python: >=3.9,<3.14
License-File: LICENSE.txt
Requires-Dist: azure-identity<2.0
Requires-Dist: ruamel-yaml<0.19,>=0.17.21
Requires-Dist: diskcache~=5.6
Requires-Dist: azure-ai-ml<2.0,>=1.30.0
Requires-Dist: azureml-assets<2.0,>=1.16.99
Dynamic: author
Dynamic: license
Dynamic: license-file
Dynamic: requires-dist
Dynamic: requires-python
Dynamic: summary
